{"code":"ATS2628_CL_S1_ON-CAMPUS","title":"Global inequality and international development","activity_data":[{"unitCode":"ATS2628_CL_S1_ON-CAMPUS","type":"Workshop","series":"01_OnCampus","part":"","day":2,"startTime":"08:00","duration":2,"weeks":"4\/3\/25 to 15\/4\/25, 29\/4\/25 to 27\/5\/25","location":"CL_19Anc\/221"},{"unitCode":"ATS2628_CL_S1_ON-CAMPUS","type":"Workshop","series":"02_OnCampus","part":"","day":2,"startTime":"10:00","duration":2,"weeks":"4\/3\/25 to 15\/4\/25, 29\/4\/25 to 27\/5\/25","location":"CL_19Anc\/221"}]}