{"code":"EAE4060_CL_S1_IMMERS-BLK","title":"Advanced field geology","activity_data":[{"unitCode":"EAE4060_CL_S1_IMMERS-BLK","type":"Practical","series":"01_OffCampus","part":"P1","day":1,"startTime":"08:00","duration":10,"weeks":"17\/3\/25","location":""},{"unitCode":"EAE4060_CL_S1_IMMERS-BLK","type":"Practical","series":"01_OffCampus","part":"P2","day":2,"startTime":"08:00","duration":10,"weeks":"18\/3\/25","location":""},{"unitCode":"EAE4060_CL_S1_IMMERS-BLK","type":"Practical","series":"01_OffCampus","part":"P3","day":3,"startTime":"08:00","duration":10,"weeks":"19\/3\/25","location":""},{"unitCode":"EAE4060_CL_S1_IMMERS-BLK","type":"Practical","series":"01_OffCampus","part":"P4","day":4,"startTime":"08:00","duration":10,"weeks":"20\/3\/25","location":""},{"unitCode":"EAE4060_CL_S1_IMMERS-BLK","type":"Practical","series":"01_OffCampus","part":"P5","day":5,"startTime":"08:00","duration":10,"weeks":"21\/3\/25","location":""}]}
