{"code":"FIT3139_CL_S1_FLEXIBLE","title":"Computational modelling and simulation","activity_data":[{"unitCode":"FIT3139_CL_S1_FLEXIBLE","type":"Applied","series":"07_OnCampus","part":"","day":1,"startTime":"08:00","duration":2,"weeks":"3\/3\/25 to 14\/4\/25, 28\/4\/25 to 26\/5\/25","location":"CL_19Anc\/137"},{"unitCode":"FIT3139_CL_S1_FLEXIBLE","type":"Workshop","series":"01_OnCampus","part":"P1","day":1,"startTime":"10:00","duration":1,"weeks":"3\/3\/25 to 14\/4\/25, 28\/4\/25 to 26\/5\/25","location":"CL_25Exh\/C1"},{"unitCode":"FIT3139_CL_S1_FLEXIBLE","type":"Workshop","series":"01_OnlineRealTime","part":"P1","day":1,"startTime":"10:00","duration":1,"weeks":"3\/3\/25 to 14\/4\/25, 28\/4\/25 to 26\/5\/25","location":""},{"unitCode":"FIT3139_CL_S1_FLEXIBLE","type":"Applied","series":"04_OnCampus","part":"","day":1,"startTime":"14:00","duration":2,"weeks":"3\/3\/25 to 14\/4\/25, 28\/4\/25 to 26\/5\/25","location":"CL_19Anc\/137"},{"unitCode":"FIT3139_CL_S1_FLEXIBLE","type":"Applied","series":"06_OnCampus","part":"","day":1,"startTime":"16:00","duration":2,"weeks":"3\/3\/25 to 14\/4\/25, 28\/4\/25 to 26\/5\/25","location":"CL_19Anc\/137"},{"unitCode":"FIT3139_CL_S1_FLEXIBLE","type":"Applied","series":"05_OnCampus","part":"","day":2,"startTime":"08:00","duration":2,"weeks":"4\/3\/25 to 15\/4\/25, 29\/4\/25 to 27\/5\/25","location":"CL_19Anc\/137"},{"unitCode":"FIT3139_CL_S1_FLEXIBLE","type":"Applied","series":"09_OnCampus","part":"","day":2,"startTime":"10:00","duration":2,"weeks":"4\/3\/25 to 15\/4\/25, 29\/4\/25 to 27\/5\/25","location":"CL_19Anc\/137"},{"unitCode":"FIT3139_CL_S1_FLEXIBLE","type":"Applied","series":"08_OnCampus","part":"","day":3,"startTime":"08:00","duration":2,"weeks":"5\/3\/25 to 16\/4\/25, 30\/4\/25 to 28\/5\/25","location":"CL_19Anc\/137"},{"unitCode":"FIT3139_CL_S1_FLEXIBLE","type":"Applied","series":"10_OnCampus","part":"","day":3,"startTime":"10:00","duration":2,"weeks":"5\/3\/25 to 16\/4\/25, 30\/4\/25 to 28\/5\/25","location":"CL_19Anc\/137"},{"unitCode":"FIT3139_CL_S1_FLEXIBLE","type":"Workshop","series":"01_OnCampus","part":"P2","day":4,"startTime":"11:00","duration":1,"weeks":"6\/3\/25 to 17\/4\/25, 1\/5\/25 to 29\/5\/25","location":"CL_16Rnf\/S3"},{"unitCode":"FIT3139_CL_S1_FLEXIBLE","type":"Workshop","series":"01_OnlineRealTime","part":"P2","day":4,"startTime":"11:00","duration":1,"weeks":"6\/3\/25 to 17\/4\/25, 1\/5\/25 to 29\/5\/25","location":""},{"unitCode":"FIT3139_CL_S1_FLEXIBLE","type":"Applied","series":"02_DualMode","part":"P1","day":5,"startTime":"12:00","duration":2,"weeks":"7\/3\/25 to 11\/4\/25, 2\/5\/25 to 30\/5\/25","location":"CL_19Anc\/137"},{"unitCode":"FIT3139_CL_S1_FLEXIBLE","type":"Applied","series":"01_DualMode","part":"P1","day":5,"startTime":"14:00","duration":2,"weeks":"7\/3\/25 to 11\/4\/25, 2\/5\/25 to 30\/5\/25","location":"CL_19Anc\/137"},{"unitCode":"FIT3139_CL_S1_FLEXIBLE","type":"Applied","series":"03_DualMode","part":"P1","day":5,"startTime":"16:00","duration":2,"weeks":"7\/3\/25 to 11\/4\/25, 2\/5\/25 to 30\/5\/25","location":"CL_19Anc\/137"},{"unitCode":"FIT3139_CL_S1_FLEXIBLE","type":"Applied","series":"03_DualMode","part":"P90","day":1,"startTime":"12:00","duration":2,"weeks":"14\/4\/25","location":""},{"unitCode":"FIT3139_CL_S1_FLEXIBLE","type":"Applied","series":"01_DualMode","part":"P90","day":2,"startTime":"18:00","duration":2,"weeks":"15\/4\/25","location":""},{"unitCode":"FIT3139_CL_S1_FLEXIBLE","type":"Applied","series":"02_DualMode","part":"P90","day":3,"startTime":"16:00","duration":2,"weeks":"16\/4\/25","location":""}]}